api_pocketcasts/__init__.py
api_pocketcasts/client.py
api_pocketcasts/exceptions.py
api_pocketcasts/endpoints/__init__.py
api_pocketcasts/endpoints/auth.py
api_pocketcasts/endpoints/bookmarks.py
api_pocketcasts/endpoints/discover.py
api_pocketcasts/endpoints/playlists.py
api_pocketcasts/endpoints/podcasts.py
api_pocketcasts/endpoints/stats.py
api_pocketcasts/endpoints/upnext.py
api_pocketcasts/models/__init__.py
api_pocketcasts/models/bookmark.py
api_pocketcasts/models/episode.py
api_pocketcasts/models/playlist.py
api_pocketcasts/models/podcast.py
api_pocketcasts/models/recommend.py
api_pocketcasts/models/stat.py
api_pocketcasts/models/user.py
api_pocketcasts-0.1.11.dist-info/licenses/LICENSE
api_pocketcasts-0.1.11.dist-info/METADATA
api_pocketcasts-0.1.11.dist-info/WHEEL
api_pocketcasts-0.1.11.dist-info/top_level.txt
api_pocketcasts-0.1.11.dist-info/RECORD
