Metadata-Version: 2.4
Name: api_pocketcasts
Version: 0.1.11
Summary: A modern, stateless Python client for the Pocket Casts API. Provides a sync client, supports authentication, podcast and episode management, and user account features. No local caching or persistent storage. Python 3.7+ required.
Author: yfhyou
Requires-Python: >=3.7
License-File: LICENSE
Requires-Dist: httpx
Requires-Dist: attrs
Dynamic: license-file
